streamlit_gchart/__init__.py
streamlit_gchart/streamlit_gchart.py
streamlit_gchart/frontend/build/asset-manifest.json
streamlit_gchart/frontend/build/bootstrap.min.css
streamlit_gchart/frontend/build/index.html
streamlit_gchart/frontend/build/static/js/2.82f4937d.chunk.js
streamlit_gchart/frontend/build/static/js/2.82f4937d.chunk.js.LICENSE.txt
streamlit_gchart/frontend/build/static/js/2.82f4937d.chunk.js.map
streamlit_gchart/frontend/build/static/js/main.5ae4cced.chunk.js
streamlit_gchart/frontend/build/static/js/main.5ae4cced.chunk.js.map
streamlit_gchart/frontend/build/static/js/runtime-main.1c2947cd.js
streamlit_gchart/frontend/build/static/js/runtime-main.1c2947cd.js.map
streamlit_gchart-0.1.8.dist-info/METADATA
streamlit_gchart-0.1.8.dist-info/WHEEL
streamlit_gchart-0.1.8.dist-info/top_level.txt
streamlit_gchart-0.1.8.dist-info/RECORD
