Metadata-Version: 2.1
Name: streamlit-gchart
Version: 0.1.8
Summary: Google Charts wordtree component for Streamlit
Home-page: https://github.com/consultimi/streamlit-gchart
Author: Miles Gard
Author-email: miles@consultimi.com
License: UNKNOWN
Platform: UNKNOWN
Requires-Python: >=3.6
